dbxslackmessage/__init__.py
dbxslackmessage/slackmessage.py
dbxslackmessage-0.1.6.dist-info/METADATA
dbxslackmessage-0.1.6.dist-info/WHEEL
dbxslackmessage-0.1.6.dist-info/top_level.txt
dbxslackmessage-0.1.6.dist-info/RECORD
